{
    "taskDefinitionArn": "arn:aws:ecs:ap-east-1:678966922805:task-definition/demo_deploy:9",
    "containerDefinitions": [
        {
            "name": "demo_deploy",
            "image": "678966922805.dkr.ecr.ap-east-1.amazonaws.com/demo_deploy:67c5fb6988dedd6ff906318fc6dd9740a574a200",
            "cpu": 0,
            "portMappings": [
                {
                    "name": "demo_deploy-80-tcp",
                    "containerPort": 80,
                    "hostPort": 80,
                    "protocol": "tcp",
                    "appProtocol": "http"
                }
            ],
            "essential": true,
            "environment": [],
            "mountPoints": [],
            "volumesFrom": [],
            "logConfiguration": {
                "logDriver": "awslogs",
                "options": {
                    "awslogs-group": "/ecs/demo_deploy",
                    "awslogs-create-group": "true",
                    "awslogs-region": "ap-east-1",
                    "awslogs-stream-prefix": "ecs"
                }
            }
        }
    ],
    "family": "demo_deploy",
    "executionRoleArn": "arn:aws:iam::678966922805:role/ecsTaskExecutionRole",
    "networkMode": "awsvpc",
    "revision": 9,
    "volumes": [],
    "status": "ACTIVE",
    "requiresAttributes": [
        {
            "name": "com.amazonaws.ecs.capability.logging-driver.awslogs"
        },
        {
            "name": "ecs.capability.execution-role-awslogs"
        },
        {
            "name": "com.amazonaws.ecs.capability.ecr-auth"
        },
        {
            "name": "com.amazonaws.ecs.capability.docker-remote-api.1.19"
        },
        {
            "name": "ecs.capability.execution-role-ecr-pull"
        },
        {
            "name": "com.amazonaws.ecs.capability.docker-remote-api.1.18"
        },
        {
            "name": "ecs.capability.task-eni"
        },
        {
            "name": "com.amazonaws.ecs.capability.docker-remote-api.1.29"
        }
    ],
    "placementConstraints": [],
    "compatibilities": [
        "EC2",
        "FARGATE"
    ],
    "requiresCompatibilities": [
        "FARGATE"
    ],
    "cpu": "1024",
    "memory": "3072",
    "runtimePlatform": {
        "cpuArchitecture": "X86_64",
        "operatingSystemFamily": "LINUX"
    },
    "registeredAt": "2023-04-06T01:06:10.281Z",
    "registeredBy": "arn:aws:iam::678966922805:root",
    "tags": []
}